syncat/__init__.py
syncat/__main__.py
syncat/solarized256.py
syncat-1.0.2.dist-info/LICENSE
syncat-1.0.2.dist-info/METADATA
syncat-1.0.2.dist-info/WHEEL
syncat-1.0.2.dist-info/entry_points.txt
syncat-1.0.2.dist-info/top_level.txt
syncat-1.0.2.dist-info/RECORD
