Metadata-Version: 2.1
Name: syncat
Version: 1.0.2
Summary: Command line interface similar to ``cat`` with syntax highlighting
Home-page: https://github.com/sivel/syncat
Author: Matt Martz
Author-email: matt@sivel.net
License: Apache License, Version 2.0
Keywords: syntac highlighting syncat cat
Platform: UNKNOWN
Classifier: Development Status :: 5 - Production/Stable
Classifier: Programming Language :: Python
Classifier: Environment :: Console
Classifier: License :: OSI Approved :: Apache Software License
Classifier: Operating System :: OS Independent
Classifier: Programming Language :: Python :: 2.7
Classifier: Programming Language :: Python :: 3.5
Classifier: Programming Language :: Python :: 3.6
Requires-Dist: pygments
